inputconditioner.v
//------------------------------------------------------------------------
// Input Conditioner
//    1) Synchronizes input to clock domain
//    2) Debounces input
//    3) Creates pulses at edge transitions
//------------------------------------------------------------------------

module inputconditioner
(
input 	    clk,            // Clock domain to synchronize input to
input	    noisysignal,    // (Potentially) noisy input signal
output reg  conditioned = 0,    // Conditioned output signal
output reg  positiveedge = 0,   // 1 clk pulse at rising edge of conditioned
output reg  negativeedge = 0    // 1 clk pulse at falling edge of conditioned
);

/*Modify the module so that the positiveedge and negativeedge output signals
are correctly generated. These signals should be high for exactly one clock
period when conditioned has a positive/negative edge, starting in the same
clock period that conditioned transitions.

Note: There are several possible ways to generate the edge signals.
Remember that assign statements are continuous and operate on wires,
while assignments in always blocks (e.g. nonblocking <=) operate on regs.
*/

    parameter counterwidth = 3; // Counter size, in bits, >= log2(waittime)
    parameter waittime = 3;     // Debounce delay, in clock cycles

    reg[counterwidth-1:0] counter = 0;
    reg synchronizer0 = 0;
    reg synchronizer1 = 0;

    always @(posedge clk) begin
        positiveedge <= 0;
        negativeedge <= 0;
        if(conditioned == synchronizer1)
            counter <= 0;
        else begin
            if( counter == waittime) begin
                counter <= 0;
                conditioned <= synchronizer1;
                positiveedge <= synchronizer1;
                negativeedge <= !synchronizer1;
            end
            else
                counter <= counter+1;
        end
        synchronizer0 <= noisysignal;
        synchronizer1 <= synchronizer0;
    end
endmodule

inputconditioner.t.v
//------------------------------------------------------------------------
// Input Conditioner test bench
//------------------------------------------------------------------------
`timescale 1 ns / 1 ps
`include "inputconditioner.v"

module testConditioner();

    reg clk;
    reg pin;
    wire conditioned;
    wire rising;
    wire falling;

    inputconditioner dut(.clk(clk),
    			 .noisysignal(pin),
			 .conditioned(conditioned),
			 .positiveedge(rising),
			 .negativeedge(falling));


    // Generate clock (50MHz)
    initial clk=0;
    always #10 clk=!clk;    // 50MHz Clock

    initial begin
    // Your Test Code
    // Be sure to test each of the three conditioner functions:
    // Synchronization, Debouncing, Edge Detection
    // 200 nanoseconds
    $dumpfile("inputconditioner.vcd");
    $dumpvars();
    pin=0; #200
    pin=1; #25
    pin=0; #200
    pin=1; #200
    pin=0; #25
    pin=1; #200
    pin=0; #200
    // if(conditioned != 1'b0)
    // $display("ADD test 1 - carryout: %h, expected: 0", carryout);
    // end
    $finish();
    end
endmodule

inputconditioner.vcd
$date
	Mon Oct  8 19:25:49 2018
$end
$version
	Icarus Verilog
$end
$timescale
	1ps
$end
$scope module testConditioner $end
$var wire 1 ! rising $end
$var wire 1 " falling $end
$var wire 1 # conditioned $end
$var reg 1 $ clk $end
$var reg 1 % pin $end
$scope module dut $end
$var wire 1 $ clk $end
$var wire 1 % noisysignal $end
$var reg 1 # conditioned $end
$var reg 3 & counter [2:0] $end
$var reg 1 " negativeedge $end
$var reg 1 ! positiveedge $end
$var reg 1 ' synchronizer0 $end
$var reg 1 ( synchronizer1 $end
$upscope $end
$upscope $end
$enddefinitions $end
#0
$dumpvars
0(
0'
b0 &
0%
0$
0#
0"
0!
$end
#10000
1$
#20000
0$
#30000
1$
#40000
0$
#50000
1$
#60000
0$
#70000
1$
#80000
0$
#90000
1$
#100000
0$
#110000
1$
#120000
0$
#130000
1$
#140000
0$
#150000
1$
#160000
0$
#170000
1$
#180000
0$
#190000
1$
#200000
0$
1%
#210000
1'
1$
#220000
0$
#225000
0%
#230000
1(
0'
1$
#240000
0$
#250000
0(
b1 &
1$
#260000
0$
#270000
b0 &
1$
#280000
0$
#290000
1$
#300000
0$
#310000
1$
#320000
0$
#330000
1$
#340000
0$
#350000
1$
#360000
0$
#370000
1$
#380000
0$
#390000
1$
#400000
0$
#410000
1$
#420000
0$
#425000
1%
#430000
1'
1$
#440000
0$
#450000
1(
1$
#460000
0$
#470000
b1 &
1$
#480000
0$
#490000
b10 &
1$
#500000
0$
#510000
b11 &
1$
#520000
0$
#530000
1!
1#
b0 &
1$
#540000
0$
#550000
0!
1$
#560000
0$
#570000
1$
#580000
0$
#590000
1$
#600000
0$
#610000
1$
#620000
0$
#625000
0%
#630000
0'
1$
#640000
0$
#650000
0(
1'
1$
1%
#660000
0$
#670000
1(
b1 &
1$
#680000
0$
#690000
b0 &
1$
#700000
0$
#710000
1$
#720000
0$
#730000
1$
#740000
0$
#750000
1$
#760000
0$
#770000
1$
#780000
0$
#790000
1$
#800000
0$
#810000
1$
#820000
0$
#830000
1$
#840000
0$
#850000
0'
1$
0%
#860000
0$
#870000
0(
1$
#880000
0$
#890000
b1 &
1$
#900000
0$
#910000
b10 &
1$
#920000
0$
#930000
b11 &
1$
#940000
0$
#950000
1"
0#
b0 &
1$
#960000
0$
#970000
0"
1$
